{
  "nightly": {
    "description": "Every commit to develop",
    "hide": false,
    "last_updated": "2025-12-26T15:38:25.000Z",
    "last_updated_url": "https://github.com/hotio/sabnzbd/actions/runs/20524709854",
    "latest": false,
    "tags": [
      "nightly",
      "nightly-a637d218c40af29279468a17a1e3ee2dbc976557",
      "nightly-b91545b"
    ]
  },
  "release": {
    "description": "Releases",
    "hide": false,
    "last_updated": "2025-12-26T15:29:57.000Z",
    "last_updated_url": "https://github.com/hotio/sabnzbd/actions/runs/20524710220",
    "latest": true,
    "tags": [
      "release",
      "release-4.5.5",
      "release-b71606d"
    ]
  },
  "testing": {
    "description": "Pre-releases",
    "hide": false,
    "last_updated": "2025-12-26T15:44:05.000Z",
    "last_updated_url": "https://github.com/hotio/sabnzbd/actions/runs/20524710553",
    "latest": false,
    "tags": [
      "testing",
      "testing-4.6.0Beta2",
      "testing-361ab8b"
    ]
  }
}
